phantom_scheduler
