Metadata-Version: 1.0
Name: phantom-scheduler
Version: 0.1.3
Summary: Artificial scheduler for clusters
Home-page: http://www2.compute.dtu.dk/~dabi/
Author: Daniele Bigoni
Author-email: dabi@dtu.dk
License: COPYING.LESSER
Platform: UNKNOWN
